promiseapi/__init__.py
promiseapi-1.0.0.dist-info/LICENSE
promiseapi-1.0.0.dist-info/METADATA
promiseapi-1.0.0.dist-info/WHEEL
promiseapi-1.0.0.dist-info/top_level.txt
promiseapi-1.0.0.dist-info/RECORD
