Metadata-Version: 2.1
Name: promiseapi
Version: 1.0.0
Summary: Kind of like JavaScript promises (in Python!)
Author-email: Carl Furtado <carlzfurtado@gmail.com>
License: MIT License
Project-URL: Homepage, https://github.com/User0332/promiseapi
Keywords: javascript,promise,async
Requires-Python: >=3.9
License-File: LICENSE
